django_modeler/__init__.py
django_modeler/cli.py
django_modeler/graph.py
django_modeler/modeler.py
django_modeler/models.py
django_modeler/tests.py
django_modeler/views.py
django_modeler-0.12.dist-info/METADATA
django_modeler-0.12.dist-info/WHEEL
django_modeler-0.12.dist-info/entry_points.txt
django_modeler-0.12.dist-info/top_level.txt
django_modeler-0.12.dist-info/RECORD
